Metadata-Version: 2.1
Name: RoboCupDBA
Version: 0.3
Summary: A small example package MongoDB Robo
Home-page: https://github.com/bluebox-dev/RoboCupDBA
Author: blueboxdev
Author-email: thanakorn.vsalab@gmail.com
Classifier: Programming Language :: Python :: 3
Classifier: License :: OSI Approved :: MIT License
Classifier: Operating System :: OS Independent
Requires-Dist: dnspython
Requires-Dist: install
Requires-Dist: pymongo
